[
  {
    "id": "331865640",
    "screenName": "aaronburnett",
    "name": "Aaron Burnett",
    "description": "Founder, CEO @mach33 | Research and Investment in Expansion Technologies",
    "location": "Merrit Island, FL",
    "website": "https://www.33fg.com/",
    "followers": 25773,
    "following": 616,
    "tweets": 8568,
    "verified": true,
    "avatarUrl": "https://pbs.twimg.com/profile_images/2049987217477513216/GJx9_LdR_normal.jpg",
    "tags": [
      "mach33"
    ],
    "org": "mach33 / 33fg",
    "source": "fxtwitter",
    "updatedAt": "2026-07-17T09:09:42.908Z"
  },
  {
    "id": "985281530070265862",
    "screenName": "dylan522p",
    "name": "Dylan Patel",
    "description": "SemiAnalysis\nBoutique AI Infrastructure Research and Consulting\nDMs are open for consulting, quotes, or to talk shop,\nOpinions my own",
    "website": "http://www.semianalysis.com/",
    "followers": 151575,
    "following": 1020,
    "tweets": 13878,
    "verified": true,
    "avatarUrl": "https://pbs.twimg.com/profile_images/1903585505046093824/PTqeS09L_normal.jpg",
    "tags": [
      "semianalysis"
    ],
    "org": "SemiAnalysis",
    "source": "fxtwitter",
    "updatedAt": "2026-07-17T09:07:53.554Z"
  },
  {
    "id": "handle:SemiAnalysis_",
    "screenName": "SemiAnalysis_",
    "name": "SemiAnalysis",
    "website": "https://www.semianalysis.com",
    "followers": 136463,
    "tags": [
      "semianalysis"
    ],
    "org": "SemiAnalysis",
    "source": "grok-export",
    "updatedAt": "2026-07-17T06:16:01.653Z"
  },
  {
    "id": "handle:mach33",
    "screenName": "mach33",
    "name": "Mach33 Financial Group",
    "description": "We research and invest in companies developing expansion technologies shaping the future of humanity, including space, AI, robotics, and advanced infrastructure",
    "website": "https://www.33fg.com/",
    "followers": 384,
    "tags": [
      "mach33"
    ],
    "org": "mach33",
    "source": "grok-export",
    "updatedAt": "2026-07-17T08:20:39.004Z"
  },
  {
    "id": "handle:VladSaigau",
    "screenName": "VladSaigau",
    "name": "Vlad Saigau",
    "description": "Space Investor @Mach33 | @yale grad",
    "website": "https://research.33fg.com/",
    "followers": 3709,
    "tags": [
      "mach33"
    ],
    "org": "mach33",
    "source": "grok-export",
    "updatedAt": "2026-07-17T08:20:39.004Z"
  },
  {
    "id": "1820488892967174144",
    "screenName": "AndrewGSugrue",
    "name": "Andrew Sugrue",
    "description": "Founder of Avenir @avenir_growth",
    "followers": 400,
    "following": 179,
    "tweets": 78,
    "verified": true,
    "avatarUrl": "https://pbs.twimg.com/profile_images/1981101773679886336/zeVAmp5p_normal.jpg",
    "tags": [],
    "source": "fxtwitter",
    "updatedAt": "2026-07-17T09:07:14.368Z"
  },
  {
    "id": "615818451",
    "screenName": "alexandr_wang",
    "name": "Alexandr Wang",
    "description": "chief ai officer @meta, founder meta superintelligence labs, founder @scale_ai. rational in the fullness of time",
    "location": "San Francisco, CA",
    "website": "https://scale.com",
    "followers": 559194,
    "following": 864,
    "tweets": 2501,
    "verified": true,
    "avatarUrl": "https://pbs.twimg.com/profile_images/1631421210205749248/uohbT_40_normal.jpg",
    "tags": [],
    "source": "fxtwitter",
    "updatedAt": "2026-07-17T09:07:17.675Z"
  },
  {
    "id": "954060455831580672",
    "screenName": "MollySOShea",
    "name": "Molly O’Shea",
    "description": "Investing & Tech →Newsletter/Podcast @Sourceryy | HUGE Fan @brexhq @Turingcom @public @deel",
    "location": "LA / NYC / SF",
    "website": "https://linktr.ee/sourceryvc",
    "followers": 65352,
    "following": 880,
    "tweets": 21005,
    "verified": true,
    "avatarUrl": "https://pbs.twimg.com/profile_images/1673061505351450624/2A8YvQ2N_normal.jpg",
    "tags": [],
    "source": "fxtwitter",
    "updatedAt": "2026-07-17T09:07:20.592Z"
  },
  {
    "id": "1745106082790318080",
    "screenName": "SemiAnalysis_",
    "name": "SemiAnalysis",
    "website": "https://www.semianalysis.com",
    "followers": 136539,
    "following": 27,
    "tweets": 2774,
    "verified": true,
    "avatarUrl": "https://pbs.twimg.com/profile_images/2062973370157694976/CdplNoi1_normal.jpg",
    "tags": [],
    "source": "fxtwitter",
    "updatedAt": "2026-07-17T09:08:30.250Z"
  },
  {
    "id": "2039137985179127808",
    "screenName": "SassineGhazi",
    "name": "Sassine Ghazi",
    "description": "President and CEO of @Synopsys",
    "location": "Sunnyvale, CA",
    "website": "https://www.synopsys.com/",
    "followers": 150,
    "following": 139,
    "tweets": 7,
    "verified": true,
    "avatarUrl": "https://pbs.twimg.com/profile_images/2042623448225320962/7cyihrMH_normal.jpg",
    "tags": [],
    "source": "fxtwitter",
    "updatedAt": "2026-07-17T09:07:38.347Z"
  },
  {
    "id": "1406609399192297475",
    "screenName": "gianlucabencomo",
    "name": "Gianluca",
    "description": "Founder @EfferenceAI | CS PhD Student @Princeton",
    "location": "San Francisco, CA",
    "website": "https://gianlucabencomo.github.io/",
    "followers": 769,
    "following": 253,
    "tweets": 217,
    "verified": true,
    "avatarUrl": "https://pbs.twimg.com/profile_images/1985051524956078080/gk12N0Aw_normal.jpg",
    "tags": [],
    "source": "fxtwitter",
    "updatedAt": "2026-07-17T09:07:57.388Z"
  },
  {
    "id": "1496125256624484362",
    "screenName": "VladSaigau",
    "name": "Vlad Saigau",
    "description": "Space Investor @Mach33 | @yale grad | 🇬🇧🇷🇴",
    "location": "London, England",
    "website": "https://research.33fg.com/",
    "followers": 3709,
    "following": 465,
    "tweets": 1798,
    "verified": true,
    "avatarUrl": "https://pbs.twimg.com/profile_images/2048709268069916672/Nz_BJSKj_normal.jpg",
    "tags": [
      "mach33"
    ],
    "org": "mach33 / 33fg",
    "source": "fxtwitter",
    "updatedAt": "2026-07-17T09:10:00.210Z"
  },
  {
    "id": "2051360039869276160",
    "screenName": "mach33",
    "name": "Mach33 Financial Group",
    "description": "We research and invest in companies developing expansion technologies shaping the future of humanity, including space, AI, robotics, and advanced infrastructure",
    "location": "Florida",
    "website": "https://www.33fg.com/",
    "followers": 384,
    "following": 3,
    "tweets": 14,
    "verified": true,
    "avatarUrl": "https://pbs.twimg.com/profile_images/2054270599107608576/SOrzE1wC_normal.jpg",
    "tags": [],
    "source": "fxtwitter",
    "updatedAt": "2026-07-17T09:09:22.830Z"
  },
  {
    "id": "44196397",
    "screenName": "elonmusk",
    "name": "Elon Musk",
    "description": "Starmind",
    "website": "https://www.spacex.com/spacexai/starmind#power-generation",
    "followers": 240917203,
    "following": 1370,
    "tweets": 105664,
    "verified": true,
    "avatarUrl": "https://pbs.twimg.com/profile_images/2053244804520427520/m8mdWZCG_normal.jpg",
    "tags": [],
    "source": "fxtwitter",
    "updatedAt": "2026-07-17T09:09:27.557Z"
  }
]
